ovos_PHAL_plugin_balena_wifi/__init__.py
ovos_PHAL_plugin_balena_wifi/version.py
ovos_PHAL_plugin_balena_wifi/gui/all/1_phone_connect-to-ap.png
ovos_PHAL_plugin_balena_wifi/gui/all/3_phone_choose-wifi.png
ovos_PHAL_plugin_balena_wifi/gui/qt5/1_phone_connect-to-ap.png
ovos_PHAL_plugin_balena_wifi/gui/qt5/3_phone_choose-wifi.png
ovos_PHAL_plugin_balena_wifi/gui/qt5/NetworkLoader.qml
ovos_PHAL_plugin_balena_wifi/gui/qt5/Prompt.qml
ovos_PHAL_plugin_balena_wifi/gui/qt5/Status.qml
ovos_PHAL_plugin_balena_wifi/gui/qt5/icons/check-circle.svg
ovos_PHAL_plugin_balena_wifi/gui/qt5/icons/info-circle.svg
ovos_PHAL_plugin_balena_wifi/gui/qt5/icons/times-circle.svg
ovos_PHAL_plugin_balena_wifi/locale/ca-es/debug_ap_created.dialog
ovos_PHAL_plugin_balena_wifi/locale/ca-es/debug_ap_start.dialog
ovos_PHAL_plugin_balena_wifi/locale/ca-es/debug_ap_stop.dialog
ovos_PHAL_plugin_balena_wifi/locale/ca-es/debug_ap_stopped.dialog
ovos_PHAL_plugin_balena_wifi/locale/ca-es/debug_connecting.dialog
ovos_PHAL_plugin_balena_wifi/locale/ca-es/debug_end_setup.dialog
ovos_PHAL_plugin_balena_wifi/locale/ca-es/debug_http_started.dialog
ovos_PHAL_plugin_balena_wifi/locale/ca-es/debug_start_setup.dialog
ovos_PHAL_plugin_balena_wifi/locale/ca-es/debug_user_connected.dialog
ovos_PHAL_plugin_balena_wifi/locale/ca-es/debug_wifi_connected.dialog
ovos_PHAL_plugin_balena_wifi/locale/ca-es/debug_wifi_error.dialog
ovos_PHAL_plugin_balena_wifi/locale/ca-es/debug_wifi_scanned.dialog
ovos_PHAL_plugin_balena_wifi/locale/ca-es/launch_setup.intent
ovos_PHAL_plugin_balena_wifi/locale/ca-es/wifi_intro.dialog
ovos_PHAL_plugin_balena_wifi/locale/ca-es/wifi_intro_2.dialog
ovos_PHAL_plugin_balena_wifi/locale/ca-es/wifi_intro_3.dialog
ovos_PHAL_plugin_balena_wifi/locale/da/debug_ap_created.dialog
ovos_PHAL_plugin_balena_wifi/locale/da/debug_ap_start.dialog
ovos_PHAL_plugin_balena_wifi/locale/da/debug_ap_stop.dialog
ovos_PHAL_plugin_balena_wifi/locale/da/debug_ap_stopped.dialog
ovos_PHAL_plugin_balena_wifi-1.2.2.dist-info/LICENSE
ovos_PHAL_plugin_balena_wifi-1.2.2.dist-info/METADATA
ovos_PHAL_plugin_balena_wifi-1.2.2.dist-info/WHEEL
ovos_PHAL_plugin_balena_wifi-1.2.2.dist-info/entry_points.txt
ovos_PHAL_plugin_balena_wifi-1.2.2.dist-info/top_level.txt
ovos_PHAL_plugin_balena_wifi-1.2.2.dist-info/zip-safe
ovos_PHAL_plugin_balena_wifi-1.2.2.dist-info/RECORD
