Metadata-Version: 2.1
Name: ovos-PHAL-plugin-balena-wifi
Version: 1.2.2
Summary: Balena wifi plugin for OpenVoiceOS hardware abstraction layer
Home-page: https://github.com/OpenVoiceOS/ovos-PHAL-plugin-balena-wifi
Author: JarbasAi
Author-email: jarbasai@mailfence.com
License: Apache-2.0
Classifier: Development Status :: 3 - Alpha
Classifier: Intended Audience :: Developers
Classifier: Topic :: System :: Networking
Classifier: License :: OSI Approved :: Apache Software License
Classifier: Programming Language :: Python :: 3.5
Classifier: Programming Language :: Python :: 3.6
Classifier: Programming Language :: Python :: 3.7
Classifier: Programming Language :: Python :: 3.8
Classifier: Programming Language :: Python :: 3.9
Classifier: Programming Language :: Python :: 3.10
License-File: LICENSE
Requires-Dist: ovos-plugin-manager<2.0.0,>=0.0.1
Requires-Dist: ovos-bus-client<2.0.0,>=0.0.6
Requires-Dist: ovos-utils<1.0.0,>=0.0.1
